receiptkit/__init__.py
receiptkit/cli.py
receiptkit/receipts.py
modly-0.1.0.dist-info/METADATA
modly-0.1.0.dist-info/WHEEL
modly-0.1.0.dist-info/entry_points.txt
modly-0.1.0.dist-info/top_level.txt
modly-0.1.0.dist-info/RECORD
