Metadata-Version: 2.4
Name: modly
Version: 0.1.0
Summary: Signed provenance receipts for LLM calls with policies and drift checks
Author: World Modeler
Requires-Python: >=3.10
Requires-Dist: pyyaml>=6.0
Requires-Dist: jsonschema>=4.0
